{
  "schemaVersion": "v5",
  "themeId": "T_068",
  "themeName": "K방산소부장",
  "meta": {
    "periodDefault": "3d",
    "periodOptions": [
      "1d",
      "3d",
      "7d",
      "15d",
      "1m",
      "ytd",
      "1y",
      "2y",
      "3y"
    ],
    "dataAsOf": "2026-03-25T00:00:00+09:00",
    "notes": "g68 누적 import 기반 K방산 소부장 테마",
    "sources": []
  },
  "nodes": [
    {
      "id": "T_068",
      "type": "THEME",
      "name": "K방산소부장"
    },
    {
      "id": "A_570",
      "type": "ASSET",
      "name": "코츠테크놀로지",
      "exposure": {
        "ticker": "448710",
        "exchange": "KOSDAQ",
        "country": "KR"
      },
      "metrics": {
        "return_1d": null,
        "close": 10170,
        "marketCap": null,
        "pe_ttm": null,
        "valuationAsOf": "2026-07-14",
        "valuationSource": "EODHD",
        "return_3d": -2.117420596727626,
        "return_7d": -9.35828877005348,
        "return_15d": null,
        "return_1m": -25.16556291390728,
        "return_ytd": -42.37960339943343,
        "return_1y": -57.06156163283591,
        "return_2y": null,
        "return_3y": null,
        "returnsAsOf": "2026-07-14",
        "returnsSource": "EODHD"
      }
    },
    {
      "id": "A_571",
      "type": "ASSET",
      "name": "퍼스텍",
      "exposure": {
        "ticker": "010820",
        "exchange": "KOSPI",
        "country": "KR"
      },
      "metrics": {
        "return_1d": null,
        "close": 5560,
        "marketCap": null,
        "pe_ttm": null,
        "valuationAsOf": "2026-07-14",
        "valuationSource": "EODHD",
        "return_3d": 0.5424954792043302,
        "return_7d": -8.25082508250825,
        "return_15d": null,
        "return_1m": -30.93167701863354,
        "return_ytd": 38.99999999999999,
        "return_1y": 44.41558441558442,
        "return_2y": null,
        "return_3y": 227.1692745376956,
        "returnsAsOf": "2026-07-14",
        "returnsSource": "EODHD"
      }
    },
    {
      "id": "A_572",
      "type": "ASSET",
      "name": "엠앤씨솔루션",
      "exposure": {
        "ticker": "484870",
        "exchange": "KOSPI",
        "country": "KR"
      },
      "metrics": {
        "return_1d": null,
        "close": 23400,
        "marketCap": null,
        "pe_ttm": null,
        "valuationAsOf": "2026-07-14",
        "valuationSource": "EODHD",
        "return_3d": -18.181818181818176,
        "return_7d": -14.598540145985407,
        "return_15d": null,
        "return_1m": -20.498303046471044,
        "return_ytd": -50.21276595744681,
        "return_1y": -54.807396074779,
        "return_2y": null,
        "return_3y": null,
        "returnsAsOf": "2026-07-14",
        "returnsSource": "EODHD"
      }
    },
    {
      "id": "A_573",
      "type": "ASSET",
      "name": "SNT다이내믹스",
      "exposure": {
        "ticker": "003570",
        "exchange": "KOSPI",
        "country": "KR"
      },
      "metrics": {
        "return_1d": null,
        "close": 33000,
        "marketCap": null,
        "pe_ttm": null,
        "valuationAsOf": "2026-07-14",
        "valuationSource": "EODHD",
        "return_3d": 1.071975497702904,
        "return_7d": -7.692307692307687,
        "return_15d": null,
        "return_1m": -22.89719626168224,
        "return_ytd": -25.907018993789578,
        "return_1y": -37.51231575449493,
        "return_2y": null,
        "return_3y": 445.7665903890161,
        "returnsAsOf": "2026-07-14",
        "returnsSource": "EODHD"
      }
    },
    {
      "id": "A_574",
      "type": "ASSET",
      "name": "STX엔진",
      "exposure": {
        "ticker": "077970",
        "exchange": "KOSPI",
        "country": "KR"
      },
      "metrics": {
        "return_1d": null,
        "close": 23900,
        "marketCap": null,
        "pe_ttm": null,
        "valuationAsOf": "2026-07-14",
        "valuationSource": "EODHD",
        "return_3d": -3.4343434343434343,
        "return_7d": -15.398230088495579,
        "return_15d": null,
        "return_1m": -34.78854024556617,
        "return_ytd": -28.550074738415542,
        "return_1y": 13.002364066193861,
        "return_2y": null,
        "return_3y": 294.38291139240505,
        "returnsAsOf": "2026-07-14",
        "returnsSource": "EODHD"
      }
    },
    {
      "id": "A_575",
      "type": "ASSET",
      "name": "삼양컴텍",
      "exposure": {
        "ticker": "484590",
        "exchange": "KOSDAQ",
        "country": "KR"
      },
      "metrics": {
        "return_1d": null,
        "close": 5740,
        "marketCap": null,
        "pe_ttm": null,
        "valuationAsOf": "2026-07-14",
        "valuationSource": "EODHD",
        "return_3d": -1.3745704467353903,
        "return_7d": -21.798365122615802,
        "return_15d": null,
        "return_1m": -28.60696517412935,
        "return_ytd": -57.16417910447762,
        "return_1y": null,
        "return_2y": null,
        "return_3y": null,
        "returnsAsOf": "2026-07-14",
        "returnsSource": "EODHD"
      }
    },
    {
      "id": "A_576",
      "type": "ASSET",
      "name": "풍산",
      "exposure": {
        "ticker": "103140",
        "exchange": "KOSPI",
        "country": "KR"
      },
      "metrics": {
        "return_1d": null,
        "close": 60700,
        "marketCap": null,
        "pe_ttm": null,
        "valuationAsOf": "2026-07-14",
        "valuationSource": "EODHD",
        "return_3d": -1.3008130081300862,
        "return_7d": -9.13173652694611,
        "return_15d": null,
        "return_1m": -19.60264900662252,
        "return_ytd": -42.033373770323365,
        "return_1y": -47.80557791711063,
        "return_2y": null,
        "return_3y": 117.82178217821783,
        "returnsAsOf": "2026-07-14",
        "returnsSource": "EODHD"
      }
    },
    {
      "id": "A_577",
      "type": "ASSET",
      "name": "켄코아에어로스페이스",
      "exposure": {
        "ticker": "274090",
        "exchange": "KOSDAQ",
        "country": "KR"
      },
      "metrics": {
        "return_1d": null,
        "close": 11360,
        "marketCap": null,
        "pe_ttm": null,
        "valuationAsOf": "2026-07-14",
        "valuationSource": "EODHD",
        "return_3d": -10.832025117739407,
        "return_7d": -5.333333333333334,
        "return_15d": null,
        "return_1m": -47.77011494252874,
        "return_ytd": -39.28380545163015,
        "return_1y": -9.984152139461177,
        "return_2y": null,
        "return_3y": 49.21465968586387,
        "returnsAsOf": "2026-07-14",
        "returnsSource": "EODHD"
      }
    },
    {
      "id": "A_578",
      "type": "ASSET",
      "name": "비츠로테크",
      "exposure": {
        "ticker": "042370",
        "exchange": "KOSDAQ",
        "country": "KR"
      },
      "metrics": {
        "return_1d": null,
        "close": 7920,
        "marketCap": null,
        "pe_ttm": null,
        "valuationAsOf": "2026-07-14",
        "valuationSource": "EODHD",
        "return_3d": -1.7369727047146455,
        "return_7d": -14.006514657980452,
        "return_15d": null,
        "return_1m": -31.487889273356405,
        "return_ytd": -13.157894736842103,
        "return_1y": -11.096201016069395,
        "return_2y": null,
        "return_3y": 99.59514170040487,
        "returnsAsOf": "2026-07-14",
        "returnsSource": "EODHD"
      }
    },
    {
      "id": "A_579",
      "type": "ASSET",
      "name": "RFHIC",
      "exposure": {
        "ticker": "218410",
        "exchange": "KOSDAQ",
        "country": "KR"
      },
      "metrics": {
        "return_1d": null,
        "close": 44750,
        "marketCap": null,
        "pe_ttm": null,
        "valuationAsOf": "2026-07-14",
        "valuationSource": "EODHD",
        "return_3d": -8.673469387755105,
        "return_7d": -22.577854671280274,
        "return_15d": null,
        "return_1m": -43.851944792973654,
        "return_ytd": 27.674750356633382,
        "return_1y": 70.26304449484331,
        "return_2y": null,
        "return_3y": 295.43726235741445,
        "returnsAsOf": "2026-07-14",
        "returnsSource": "EODHD"
      }
    },
    {
      "id": "A_580",
      "type": "ASSET",
      "name": "아이쓰리시스템",
      "exposure": {
        "ticker": "214430",
        "exchange": "KOSDAQ",
        "country": "KR"
      },
      "metrics": {
        "return_1d": null,
        "close": 56900,
        "marketCap": null,
        "pe_ttm": null,
        "valuationAsOf": "2026-07-14",
        "valuationSource": "EODHD",
        "return_3d": 2.3381294964028854,
        "return_7d": -6.721311475409841,
        "return_15d": null,
        "return_1m": -22.37380627557981,
        "return_ytd": -28.69674185463659,
        "return_1y": -39.75993795337131,
        "return_2y": null,
        "return_3y": 321.9570405727923,
        "returnsAsOf": "2026-07-14",
        "returnsSource": "EODHD"
      }
    },
    {
      "id": "BF_128",
      "type": "BUSINESS_FIELD",
      "name": "지상화력/기동"
    },
    {
      "id": "BF_129",
      "type": "BUSINESS_FIELD",
      "name": "유도무기·레이더·전자전"
    },
    {
      "id": "BF_130",
      "type": "BUSINESS_FIELD",
      "name": "항공/우주"
    },
    {
      "id": "M_026",
      "type": "MACRO",
      "name": "방산수요증가"
    },
    {
      "id": "M_131",
      "type": "MACRO",
      "name": "군비증강"
    },
    {
      "id": "M_150",
      "type": "MACRO",
      "name": "나토군비증강"
    }
  ],
  "edges": [
    {
      "from": "A_570",
      "to": "T_068",
      "type": "THEMED_AS",
      "evidence": [
        "EV_002161"
      ],
      "confidence": 0.8,
      "status": "verified"
    },
    {
      "from": "A_571",
      "to": "T_068",
      "type": "THEMED_AS",
      "evidence": [
        "EV_002162"
      ],
      "confidence": 0.8,
      "status": "verified"
    },
    {
      "from": "A_572",
      "to": "T_068",
      "type": "THEMED_AS",
      "evidence": [
        "EV_002163"
      ],
      "confidence": 0.8,
      "status": "verified"
    },
    {
      "from": "A_573",
      "to": "T_068",
      "type": "THEMED_AS",
      "evidence": [
        "EV_002164"
      ],
      "confidence": 0.8,
      "status": "verified"
    },
    {
      "from": "A_574",
      "to": "T_068",
      "type": "THEMED_AS",
      "evidence": [
        "EV_002165"
      ],
      "confidence": 0.8,
      "status": "verified"
    },
    {
      "from": "A_575",
      "to": "T_068",
      "type": "THEMED_AS",
      "evidence": [
        "EV_002166"
      ],
      "confidence": 0.8,
      "status": "verified"
    },
    {
      "from": "A_576",
      "to": "T_068",
      "type": "THEMED_AS",
      "evidence": [
        "EV_002167"
      ],
      "confidence": 0.8,
      "status": "verified"
    },
    {
      "from": "A_577",
      "to": "T_068",
      "type": "THEMED_AS",
      "evidence": [
        "EV_002168"
      ],
      "confidence": 0.8,
      "status": "verified"
    },
    {
      "from": "A_578",
      "to": "T_068",
      "type": "THEMED_AS",
      "evidence": [
        "EV_002169"
      ],
      "confidence": 0.8,
      "status": "verified"
    },
    {
      "from": "A_579",
      "to": "T_068",
      "type": "THEMED_AS",
      "evidence": [
        "EV_002170"
      ],
      "confidence": 0.8,
      "status": "verified"
    },
    {
      "from": "A_580",
      "to": "T_068",
      "type": "THEMED_AS",
      "evidence": [
        "EV_002171"
      ],
      "confidence": 0.8,
      "status": "verified"
    },
    {
      "from": "A_570",
      "to": "BF_128",
      "type": "OPERATES",
      "evidence": [
        "EV_002172"
      ],
      "confidence": 0.8,
      "status": "verified"
    },
    {
      "from": "A_571",
      "to": "BF_128",
      "type": "OPERATES",
      "evidence": [
        "EV_002173"
      ],
      "confidence": 0.8,
      "status": "verified"
    },
    {
      "from": "A_572",
      "to": "BF_128",
      "type": "OPERATES",
      "evidence": [
        "EV_002174"
      ],
      "confidence": 0.8,
      "status": "verified"
    },
    {
      "from": "A_573",
      "to": "BF_128",
      "type": "OPERATES",
      "evidence": [
        "EV_002175"
      ],
      "confidence": 0.8,
      "status": "verified"
    },
    {
      "from": "A_574",
      "to": "BF_128",
      "type": "OPERATES",
      "evidence": [
        "EV_002176"
      ],
      "confidence": 0.8,
      "status": "verified"
    },
    {
      "from": "A_575",
      "to": "BF_128",
      "type": "OPERATES",
      "evidence": [
        "EV_002177"
      ],
      "confidence": 0.8,
      "status": "verified"
    },
    {
      "from": "A_576",
      "to": "BF_128",
      "type": "OPERATES",
      "evidence": [
        "EV_002178"
      ],
      "confidence": 0.8,
      "status": "verified"
    },
    {
      "from": "A_580",
      "to": "BF_129",
      "type": "OPERATES",
      "evidence": [
        "EV_002179"
      ],
      "confidence": 0.8,
      "status": "verified"
    },
    {
      "from": "A_579",
      "to": "BF_129",
      "type": "OPERATES",
      "evidence": [
        "EV_002180"
      ],
      "confidence": 0.8,
      "status": "verified"
    },
    {
      "from": "A_578",
      "to": "BF_129",
      "type": "OPERATES",
      "evidence": [
        "EV_002181"
      ],
      "confidence": 0.8,
      "status": "verified"
    },
    {
      "from": "A_577",
      "to": "BF_130",
      "type": "OPERATES",
      "evidence": [
        "EV_002182"
      ],
      "confidence": 0.8,
      "status": "verified"
    },
    {
      "from": "A_578",
      "to": "BF_130",
      "type": "OPERATES",
      "evidence": [
        "EV_002183"
      ],
      "confidence": 0.8,
      "status": "verified"
    },
    {
      "from": "M_026",
      "to": "T_068",
      "type": "IMPACTS",
      "evidence": [
        "EV_002184"
      ],
      "confidence": 0.75,
      "status": "verified"
    },
    {
      "from": "M_131",
      "to": "T_068",
      "type": "IMPACTS",
      "evidence": [
        "EV_002185"
      ],
      "confidence": 0.75,
      "status": "verified"
    },
    {
      "from": "M_150",
      "to": "T_068",
      "type": "IMPACTS",
      "evidence": [
        "EV_002186"
      ],
      "confidence": 0.75,
      "status": "verified"
    }
  ],
  "links": [
    {
      "from": "A_570",
      "to": "T_068",
      "type": "THEMED_AS",
      "evidence": [
        "EV_002161"
      ],
      "confidence": 0.8,
      "status": "verified"
    },
    {
      "from": "A_571",
      "to": "T_068",
      "type": "THEMED_AS",
      "evidence": [
        "EV_002162"
      ],
      "confidence": 0.8,
      "status": "verified"
    },
    {
      "from": "A_572",
      "to": "T_068",
      "type": "THEMED_AS",
      "evidence": [
        "EV_002163"
      ],
      "confidence": 0.8,
      "status": "verified"
    },
    {
      "from": "A_573",
      "to": "T_068",
      "type": "THEMED_AS",
      "evidence": [
        "EV_002164"
      ],
      "confidence": 0.8,
      "status": "verified"
    },
    {
      "from": "A_574",
      "to": "T_068",
      "type": "THEMED_AS",
      "evidence": [
        "EV_002165"
      ],
      "confidence": 0.8,
      "status": "verified"
    },
    {
      "from": "A_575",
      "to": "T_068",
      "type": "THEMED_AS",
      "evidence": [
        "EV_002166"
      ],
      "confidence": 0.8,
      "status": "verified"
    },
    {
      "from": "A_576",
      "to": "T_068",
      "type": "THEMED_AS",
      "evidence": [
        "EV_002167"
      ],
      "confidence": 0.8,
      "status": "verified"
    },
    {
      "from": "A_577",
      "to": "T_068",
      "type": "THEMED_AS",
      "evidence": [
        "EV_002168"
      ],
      "confidence": 0.8,
      "status": "verified"
    },
    {
      "from": "A_578",
      "to": "T_068",
      "type": "THEMED_AS",
      "evidence": [
        "EV_002169"
      ],
      "confidence": 0.8,
      "status": "verified"
    },
    {
      "from": "A_579",
      "to": "T_068",
      "type": "THEMED_AS",
      "evidence": [
        "EV_002170"
      ],
      "confidence": 0.8,
      "status": "verified"
    },
    {
      "from": "A_580",
      "to": "T_068",
      "type": "THEMED_AS",
      "evidence": [
        "EV_002171"
      ],
      "confidence": 0.8,
      "status": "verified"
    },
    {
      "from": "A_570",
      "to": "BF_128",
      "type": "OPERATES",
      "evidence": [
        "EV_002172"
      ],
      "confidence": 0.8,
      "status": "verified"
    },
    {
      "from": "A_571",
      "to": "BF_128",
      "type": "OPERATES",
      "evidence": [
        "EV_002173"
      ],
      "confidence": 0.8,
      "status": "verified"
    },
    {
      "from": "A_572",
      "to": "BF_128",
      "type": "OPERATES",
      "evidence": [
        "EV_002174"
      ],
      "confidence": 0.8,
      "status": "verified"
    },
    {
      "from": "A_573",
      "to": "BF_128",
      "type": "OPERATES",
      "evidence": [
        "EV_002175"
      ],
      "confidence": 0.8,
      "status": "verified"
    },
    {
      "from": "A_574",
      "to": "BF_128",
      "type": "OPERATES",
      "evidence": [
        "EV_002176"
      ],
      "confidence": 0.8,
      "status": "verified"
    },
    {
      "from": "A_575",
      "to": "BF_128",
      "type": "OPERATES",
      "evidence": [
        "EV_002177"
      ],
      "confidence": 0.8,
      "status": "verified"
    },
    {
      "from": "A_576",
      "to": "BF_128",
      "type": "OPERATES",
      "evidence": [
        "EV_002178"
      ],
      "confidence": 0.8,
      "status": "verified"
    },
    {
      "from": "A_580",
      "to": "BF_129",
      "type": "OPERATES",
      "evidence": [
        "EV_002179"
      ],
      "confidence": 0.8,
      "status": "verified"
    },
    {
      "from": "A_579",
      "to": "BF_129",
      "type": "OPERATES",
      "evidence": [
        "EV_002180"
      ],
      "confidence": 0.8,
      "status": "verified"
    },
    {
      "from": "A_578",
      "to": "BF_129",
      "type": "OPERATES",
      "evidence": [
        "EV_002181"
      ],
      "confidence": 0.8,
      "status": "verified"
    },
    {
      "from": "A_577",
      "to": "BF_130",
      "type": "OPERATES",
      "evidence": [
        "EV_002182"
      ],
      "confidence": 0.8,
      "status": "verified"
    },
    {
      "from": "A_578",
      "to": "BF_130",
      "type": "OPERATES",
      "evidence": [
        "EV_002183"
      ],
      "confidence": 0.8,
      "status": "verified"
    },
    {
      "from": "M_026",
      "to": "T_068",
      "type": "IMPACTS",
      "evidence": [
        "EV_002184"
      ],
      "confidence": 0.75,
      "status": "verified"
    },
    {
      "from": "M_131",
      "to": "T_068",
      "type": "IMPACTS",
      "evidence": [
        "EV_002185"
      ],
      "confidence": 0.75,
      "status": "verified"
    },
    {
      "from": "M_150",
      "to": "T_068",
      "type": "IMPACTS",
      "evidence": [
        "EV_002186"
      ],
      "confidence": 0.75,
      "status": "verified"
    }
  ]
}