{
  "schemaVersion": "v5",
  "themeId": "T_098",
  "themeName": "빅머니-베일리기프트",
  "meta": {
    "periodDefault": "3d",
    "periodOptions": [
      "3d",
      "7d",
      "1m",
      "ytd",
      "1y",
      "3y"
    ],
    "dataAsOf": "2026-04-02T00:00:00+09:00",
    "notes": "g98 누적 import 기반 빅머니-베일리기프트 테마",
    "sources": []
  },
  "nodes": [
    {
      "id": "T_098",
      "type": "THEME",
      "name": "빅머니-베일리기프트"
    },
    {
      "id": "A_748",
      "type": "ASSET",
      "name": "PDD홀딩스",
      "exposure": {
        "ticker": "PDD",
        "exchange": "NASDAQ",
        "country": "US"
      },
      "metrics": {
        "close": 104.2,
        "marketCap": 146149758274,
        "pe_ttm": null,
        "valuationAsOf": "2026-04-20",
        "valuationSource": "FMP",
        "return_3d": null,
        "return_7d": null,
        "return_1m": null,
        "return_ytd": null,
        "return_1y": null,
        "return_3y": null,
        "returnsAsOf": "2026-04-20",
        "returnsSource": "FMP"
      }
    },
    {
      "id": "A_211",
      "type": "ASSET",
      "name": "아마존",
      "exposure": {
        "ticker": "AMZN",
        "exchange": "NASDAQ",
        "country": "US"
      },
      "metrics": {
        "close": 248.28,
        "marketCap": 2670065560434,
        "pe_ttm": null,
        "valuationAsOf": "2026-04-20",
        "valuationSource": "FMP",
        "return_3d": null,
        "return_7d": null,
        "return_1m": null,
        "return_ytd": null,
        "return_1y": null,
        "return_3y": null,
        "returnsAsOf": "2026-04-20",
        "returnsSource": "FMP"
      }
    },
    {
      "id": "A_019",
      "type": "ASSET",
      "name": "쿠팡",
      "exposure": {
        "ticker": "CPNG",
        "exchange": "NYSE",
        "country": "US"
      },
      "metrics": {
        "close": 21.51,
        "marketCap": 39324400477,
        "pe_ttm": null,
        "valuationAsOf": "2026-04-20",
        "valuationSource": "FMP",
        "return_3d": null,
        "return_7d": null,
        "return_1m": null,
        "return_ytd": null,
        "return_1y": null,
        "return_3y": null,
        "returnsAsOf": "2026-04-20",
        "returnsSource": "FMP"
      }
    },
    {
      "id": "A_366",
      "type": "ASSET",
      "name": "씨그룹",
      "exposure": {
        "ticker": "SE",
        "exchange": "NYSE",
        "country": "US"
      },
      "metrics": {
        "close": 89.34,
        "marketCap": 52891061082,
        "pe_ttm": null,
        "valuationAsOf": "2026-04-20",
        "valuationSource": "FMP",
        "return_3d": null,
        "return_7d": null,
        "return_1m": null,
        "return_ytd": null,
        "return_1y": null,
        "return_3y": null,
        "returnsAsOf": "2026-04-20",
        "returnsSource": "FMP"
      }
    },
    {
      "id": "A_350",
      "type": "ASSET",
      "name": "소파이",
      "exposure": {
        "ticker": "SOFI",
        "exchange": "NASDAQ",
        "country": "US"
      },
      "metrics": {
        "close": 19.5,
        "marketCap": 24867570000,
        "pe_ttm": null,
        "valuationAsOf": "2026-04-20",
        "valuationSource": "FMP",
        "return_3d": null,
        "return_7d": null,
        "return_1m": null,
        "return_ytd": null,
        "return_1y": null,
        "return_3y": null,
        "returnsAsOf": "2026-04-20",
        "returnsSource": "FMP"
      }
    },
    {
      "id": "A_367",
      "type": "ASSET",
      "name": "메르카도리브레",
      "exposure": {
        "ticker": "MELI",
        "exchange": "NASDAQ",
        "country": "US"
      },
      "metrics": {
        "close": 1870.08,
        "marketCap": 94807786115,
        "pe_ttm": null,
        "valuationAsOf": "2026-04-20",
        "valuationSource": "FMP",
        "return_3d": null,
        "return_7d": null,
        "return_1m": null,
        "return_ytd": null,
        "return_1y": null,
        "return_3y": null,
        "returnsAsOf": "2026-04-20",
        "returnsSource": "FMP"
      }
    },
    {
      "id": "A_749",
      "type": "ASSET",
      "name": "스포티파이",
      "exposure": {
        "ticker": "SPOT",
        "exchange": "NYSE",
        "country": "US"
      },
      "metrics": {
        "close": 536.76,
        "marketCap": 110509404818,
        "pe_ttm": null,
        "valuationAsOf": "2026-04-20",
        "valuationSource": "FMP",
        "return_3d": null,
        "return_7d": null,
        "return_1m": null,
        "return_ytd": null,
        "return_1y": null,
        "return_3y": null,
        "returnsAsOf": "2026-04-20",
        "returnsSource": "FMP"
      }
    },
    {
      "id": "A_278",
      "type": "ASSET",
      "name": "클라우드플레어",
      "exposure": {
        "ticker": "NET",
        "exchange": "NYSE",
        "country": "US"
      },
      "metrics": {
        "close": 204.81,
        "marketCap": 72089083195,
        "pe_ttm": null,
        "valuationAsOf": "2026-04-20",
        "valuationSource": "FMP",
        "return_3d": null,
        "return_7d": null,
        "return_1m": null,
        "return_ytd": null,
        "return_1y": null,
        "return_3y": null,
        "returnsAsOf": "2026-04-20",
        "returnsSource": "FMP"
      }
    },
    {
      "id": "A_055",
      "type": "ASSET",
      "name": "엔비디아",
      "exposure": {
        "ticker": "NVDA",
        "exchange": "NASDAQ",
        "country": "US"
      },
      "metrics": {
        "close": 202.06,
        "marketCap": 4911068128451,
        "pe_ttm": null,
        "valuationAsOf": "2026-04-20",
        "valuationSource": "FMP",
        "return_3d": null,
        "return_7d": null,
        "return_1m": null,
        "return_ytd": null,
        "return_1y": null,
        "return_3y": null,
        "returnsAsOf": "2026-04-20",
        "returnsSource": "FMP"
      }
    },
    {
      "id": "A_118",
      "type": "ASSET",
      "name": "로켓랩",
      "exposure": {
        "ticker": "RKLB",
        "exchange": "NASDAQ",
        "country": "US"
      },
      "metrics": {
        "close": 89.46,
        "marketCap": 51508115820,
        "pe_ttm": null,
        "valuationAsOf": "2026-04-20",
        "valuationSource": "FMP",
        "return_3d": null,
        "return_7d": null,
        "return_1m": null,
        "return_ytd": null,
        "return_1y": null,
        "return_3y": null,
        "returnsAsOf": "2026-04-20",
        "returnsSource": "FMP"
      }
    },
    {
      "id": "A_365",
      "type": "ASSET",
      "name": "Nu홀딩스",
      "exposure": {
        "ticker": "NU",
        "exchange": "NYSE",
        "country": "US"
      },
      "metrics": {
        "close": 15.1,
        "marketCap": 72955695874,
        "pe_ttm": null,
        "valuationAsOf": "2026-04-20",
        "valuationSource": "FMP",
        "return_3d": null,
        "return_7d": null,
        "return_1m": null,
        "return_ytd": null,
        "return_1y": null,
        "return_3y": null,
        "returnsAsOf": "2026-04-20",
        "returnsSource": "FMP"
      }
    },
    {
      "id": "C_092",
      "type": "CHARACTER",
      "name": "구조적성장테마주"
    }
  ],
  "edges": [
    {
      "from": "A_748",
      "to": "T_098",
      "type": "THEMED_AS"
    },
    {
      "from": "A_211",
      "to": "T_098",
      "type": "THEMED_AS"
    },
    {
      "from": "A_019",
      "to": "T_098",
      "type": "THEMED_AS"
    },
    {
      "from": "A_366",
      "to": "T_098",
      "type": "THEMED_AS"
    },
    {
      "from": "A_350",
      "to": "T_098",
      "type": "THEMED_AS"
    },
    {
      "from": "A_367",
      "to": "T_098",
      "type": "THEMED_AS"
    },
    {
      "from": "A_749",
      "to": "T_098",
      "type": "THEMED_AS"
    },
    {
      "from": "A_278",
      "to": "T_098",
      "type": "THEMED_AS"
    },
    {
      "from": "A_055",
      "to": "T_098",
      "type": "THEMED_AS"
    },
    {
      "from": "A_118",
      "to": "T_098",
      "type": "THEMED_AS"
    },
    {
      "from": "A_365",
      "to": "T_098",
      "type": "THEMED_AS"
    },
    {
      "from": "T_098",
      "to": "C_092",
      "type": "HAS_TRAIT"
    }
  ],
  "links": [
    {
      "from": "A_748",
      "to": "T_098",
      "type": "THEMED_AS"
    },
    {
      "from": "A_211",
      "to": "T_098",
      "type": "THEMED_AS"
    },
    {
      "from": "A_019",
      "to": "T_098",
      "type": "THEMED_AS"
    },
    {
      "from": "A_366",
      "to": "T_098",
      "type": "THEMED_AS"
    },
    {
      "from": "A_350",
      "to": "T_098",
      "type": "THEMED_AS"
    },
    {
      "from": "A_367",
      "to": "T_098",
      "type": "THEMED_AS"
    },
    {
      "from": "A_749",
      "to": "T_098",
      "type": "THEMED_AS"
    },
    {
      "from": "A_278",
      "to": "T_098",
      "type": "THEMED_AS"
    },
    {
      "from": "A_055",
      "to": "T_098",
      "type": "THEMED_AS"
    },
    {
      "from": "A_118",
      "to": "T_098",
      "type": "THEMED_AS"
    },
    {
      "from": "A_365",
      "to": "T_098",
      "type": "THEMED_AS"
    },
    {
      "from": "T_098",
      "to": "C_092",
      "type": "HAS_TRAIT"
    }
  ]
}