{
  "schemaVersion": "v5",
  "themeId": "T_115",
  "themeName": "미국미디어산업",
  "meta": {
    "periodDefault": "3d",
    "periodOptions": [
      "1d",
      "3d",
      "7d",
      "15d",
      "1m",
      "ytd",
      "1y",
      "2y",
      "3y"
    ],
    "dataAsOf": "2026-04-07T00:00:00+09:00",
    "notes": "g115 누적 import 기반 미국미디어산업 테마",
    "sources": [],
    "changelog": [
      {
        "date": "2026-07-11",
        "kind": "보강",
        "title": "자산별 테마관점 CHR 정의",
        "detail": "자산별 테마관점 CHR 정의."
      },
      {
        "date": "2026-07-11",
        "kind": "보강",
        "title": "엣지 근거 구체 백필 + 2026 이벤트",
        "detail": "전 엣지 근거를 종목별 사업·관계 사실로 구체화하고 2026 이벤트 2건을 추가했다."
      }
    ]
  },
  "nodes": [
    {
      "id": "T_115",
      "type": "THEME",
      "name": "미국미디어산업"
    },
    {
      "id": "A_828",
      "type": "ASSET",
      "name": "워너브라더스디스커버리",
      "exposure": {
        "ticker": "WBD",
        "exchange": "NASDAQ",
        "country": "US"
      },
      "metrics": {
        "return_1d": -0.11600928074246841,
        "close": 25.83,
        "marketCap": 64759341013,
        "pe_ttm": null,
        "valuationAsOf": "2026-07-21",
        "valuationSource": "FMP",
        "return_3d": -5.349945034811288,
        "return_7d": -2.858217374952998,
        "return_15d": -4.7917434574272,
        "return_1m": -1.4122137404580237,
        "return_ytd": -9.400210452472823,
        "return_1y": 102.58823529411765,
        "return_2y": 223.68421052631575,
        "return_3y": 108.30645161290322,
        "returnsAsOf": "2026-07-21",
        "returnsSource": "FMP"
      }
    },
    {
      "id": "A_829",
      "type": "ASSET",
      "name": "컴캐스트",
      "exposure": {
        "ticker": "CMCSA",
        "exchange": "NASDAQ",
        "country": "US"
      },
      "metrics": {
        "return_1d": 0.1261564339781307,
        "close": 23.81,
        "marketCap": 85054769228,
        "pe_ttm": null,
        "valuationAsOf": "2026-07-21",
        "valuationSource": "FMP",
        "return_3d": -1.2033195020746956,
        "return_7d": 1.0182435299108894,
        "return_15d": -1.6928158546655636,
        "return_1m": 6.1524743646901525,
        "return_ytd": -13.950126490784253,
        "return_1y": -31.06543138390272,
        "return_2y": -39.88891694016663,
        "return_3y": -43.3230183289693,
        "returnsAsOf": "2026-07-21",
        "returnsSource": "FMP"
      }
    },
    {
      "id": "A_830",
      "type": "ASSET",
      "name": "파라마운트글로벌",
      "exposure": {
        "ticker": "PARA",
        "exchange": "NASDAQ",
        "country": "US"
      },
      "metrics": {
        "return_1d": -10.477001703577516,
        "close": 11.04,
        "marketCap": 6994082703,
        "pe_ttm": null,
        "valuationAsOf": "2026-07-21",
        "valuationSource": "FMP",
        "return_3d": -14.760746147607462,
        "return_7d": -20.85843373493975,
        "return_15d": -18.84169884169884,
        "return_1m": -17.697729052466716,
        "return_ytd": -0.6616257088846944,
        "return_1y": 0.5741626794258492,
        "return_2y": -32.75751759436981,
        "return_3y": null,
        "returnsAsOf": "2026-07-21",
        "returnsSource": "FMP"
      }
    },
    {
      "id": "A_328",
      "type": "ASSET",
      "name": "디즈니",
      "exposure": {
        "ticker": "DIS",
        "exchange": "NYSE",
        "country": "US"
      },
      "metrics": {
        "return_1d": -0.28005393631365116,
        "close": 96.14,
        "marketCap": 166948208303,
        "pe_ttm": null,
        "valuationAsOf": "2026-07-21",
        "valuationSource": "FMP",
        "return_3d": -3.5803831110219564,
        "return_7d": 0.5438192846684675,
        "return_15d": -2.524586839703935,
        "return_1m": -7.459813264029258,
        "return_ytd": -14.045596781403658,
        "return_1y": -20.820293197166862,
        "return_2y": -2.3662029044378974,
        "return_3y": 8.485669149176257,
        "returnsAsOf": "2026-07-21",
        "returnsSource": "FMP"
      }
    },
    {
      "id": "A_326",
      "type": "ASSET",
      "name": "넷플릭스",
      "exposure": {
        "ticker": "NFLX",
        "exchange": "NASDAQ",
        "country": "US"
      },
      "metrics": {
        "return_1d": 1.5828402366864003,
        "close": 68.67,
        "marketCap": 289155636000,
        "pe_ttm": null,
        "valuationAsOf": "2026-07-21",
        "valuationSource": "FMP",
        "return_3d": -7.639542703429713,
        "return_7d": -6.405887965108359,
        "return_15d": -6.925996204933583,
        "return_1m": -11.256138537089678,
        "return_ytd": -24.53016815034619,
        "return_1y": -43.21038703274892,
        "return_2y": 4.632028035959168,
        "return_3y": 55.39714867617109,
        "returnsAsOf": "2026-07-21",
        "returnsSource": "FMP"
      }
    },
    {
      "id": "A_831",
      "type": "ASSET",
      "name": "로쿠",
      "exposure": {
        "ticker": "ROKU",
        "exchange": "NASDAQ",
        "country": "US"
      },
      "metrics": {
        "return_1d": 0.09713453132589311,
        "close": 144.27,
        "marketCap": 21401322269,
        "pe_ttm": null,
        "valuationAsOf": "2026-07-21",
        "valuationSource": "FMP",
        "return_3d": 0.31289111389236623,
        "return_7d": 2.544601606368624,
        "return_15d": 5.6690837178642095,
        "return_1m": 4.490475845585595,
        "return_ytd": 32.69867549668874,
        "return_1y": 54.646800300139354,
        "return_2y": 122.87965394716514,
        "return_3y": 94.90678195082411,
        "returnsAsOf": "2026-07-21",
        "returnsSource": "FMP"
      }
    },
    {
      "id": "A_832",
      "type": "ASSET",
      "name": "폭스",
      "exposure": {
        "ticker": "FOXA",
        "exchange": "NASDAQ",
        "country": "US"
      },
      "metrics": {
        "return_1d": 0.15657620041753528,
        "close": 57.57,
        "marketCap": 25244723812,
        "pe_ttm": null,
        "valuationAsOf": "2026-07-21",
        "valuationSource": "FMP",
        "return_3d": 1.3377926421404673,
        "return_7d": 6.37472283813747,
        "return_15d": 14.2488589005755,
        "return_1m": 10.224009190120631,
        "return_ytd": -21.949566160520618,
        "return_1y": 2.3466666666666747,
        "return_2y": 56.738361012796105,
        "return_3y": 73.45586019885508,
        "returnsAsOf": "2026-07-21",
        "returnsSource": "FMP"
      }
    },
    {
      "id": "A_833",
      "type": "ASSET",
      "name": "AMC",
      "exposure": {
        "ticker": "AMC",
        "exchange": "NYSE",
        "country": "US"
      },
      "metrics": {
        "return_1d": -10.569105691056901,
        "close": 2.2,
        "marketCap": 1347003610,
        "pe_ttm": null,
        "valuationAsOf": "2026-07-21",
        "valuationSource": "FMP",
        "return_3d": 6.280193236715004,
        "return_7d": 16.40211640211642,
        "return_15d": 8.374384236453224,
        "return_1m": -22.26148409893992,
        "return_ytd": 36.645962732919266,
        "return_1y": -37.85310734463276,
        "return_2y": -59.78062157221207,
        "return_3y": -94.91916859122402,
        "returnsAsOf": "2026-07-21",
        "returnsSource": "FMP"
      }
    },
    {
      "id": "BF_011",
      "type": "BUSINESS_FIELD",
      "name": "스트리밍"
    },
    {
      "id": "BF_218",
      "type": "BUSINESS_FIELD",
      "name": "배급"
    },
    {
      "id": "BF_219",
      "type": "BUSINESS_FIELD",
      "name": "CNN"
    },
    {
      "id": "BF_220",
      "type": "BUSINESS_FIELD",
      "name": "디스커버리"
    },
    {
      "id": "BF_221",
      "type": "BUSINESS_FIELD",
      "name": "HBO"
    },
    {
      "id": "BF_222",
      "type": "BUSINESS_FIELD",
      "name": "콘텐츠제작"
    },
    {
      "id": "BF_223",
      "type": "BUSINESS_FIELD",
      "name": "CTV광고플랫폼"
    },
    {
      "id": "BF_224",
      "type": "BUSINESS_FIELD",
      "name": "케이블/PAY"
    },
    {
      "id": "BF_225",
      "type": "BUSINESS_FIELD",
      "name": "극장"
    },
    {
      "id": "M_387",
      "type": "MACRO",
      "name": "글로벌OTT콘텐츠수요"
    },
    {
      "id": "M_038",
      "type": "MACRO",
      "name": "반독점규제"
    },
    {
      "id": "M_346",
      "type": "MACRO",
      "name": "미국소비강세"
    },
    {
      "id": "C_2230",
      "type": "CHARACTER",
      "name": "HBO_CNN분할추진"
    },
    {
      "id": "C_2231",
      "type": "CHARACTER",
      "name": "NBCU케이블피콕"
    },
    {
      "id": "C_2232",
      "type": "CHARACTER",
      "name": "파라마운트스카이댄스"
    },
    {
      "id": "C_2233",
      "type": "CHARACTER",
      "name": "스튜디오디즈니플러스파크"
    },
    {
      "id": "C_2234",
      "type": "CHARACTER",
      "name": "글로벌스트리밍1위"
    },
    {
      "id": "C_2235",
      "type": "CHARACTER",
      "name": "CTV스트리밍광고플랫폼"
    },
    {
      "id": "C_2236",
      "type": "CHARACTER",
      "name": "뉴스스포츠케이블폭스"
    },
    {
      "id": "C_2237",
      "type": "CHARACTER",
      "name": "미국최대극장체인"
    }
  ],
  "edges": [
    {
      "from": "A_828",
      "to": "T_115",
      "type": "THEMED_AS",
      "evidence": [
        "EV_003356"
      ],
      "confidence": 0.8,
      "status": "verified"
    },
    {
      "from": "A_829",
      "to": "T_115",
      "type": "THEMED_AS",
      "evidence": [
        "EV_003357"
      ],
      "confidence": 0.8,
      "status": "verified"
    },
    {
      "from": "A_830",
      "to": "T_115",
      "type": "THEMED_AS",
      "evidence": [
        "EV_003358"
      ],
      "confidence": 0.78,
      "status": "verified"
    },
    {
      "from": "A_328",
      "to": "T_115",
      "type": "THEMED_AS",
      "evidence": [
        "EV_003359"
      ],
      "confidence": 0.82,
      "status": "verified"
    },
    {
      "from": "A_326",
      "to": "T_115",
      "type": "THEMED_AS",
      "evidence": [
        "EV_003360"
      ],
      "confidence": 0.83,
      "status": "verified"
    },
    {
      "from": "A_831",
      "to": "T_115",
      "type": "THEMED_AS",
      "evidence": [
        "EV_003361"
      ],
      "confidence": 0.78,
      "status": "verified"
    },
    {
      "from": "A_832",
      "to": "T_115",
      "type": "THEMED_AS",
      "evidence": [
        "EV_003362"
      ],
      "confidence": 0.76,
      "status": "verified"
    },
    {
      "from": "A_833",
      "to": "T_115",
      "type": "THEMED_AS",
      "evidence": [
        "EV_003363"
      ],
      "confidence": 0.72,
      "status": "verified"
    },
    {
      "from": "A_828",
      "to": "BF_218",
      "type": "OPERATES",
      "evidence": [
        "EV_003364"
      ],
      "confidence": 0.76,
      "status": "verified"
    },
    {
      "from": "A_828",
      "to": "BF_219",
      "type": "OPERATES",
      "evidence": [
        "EV_003365"
      ],
      "confidence": 0.76,
      "status": "verified"
    },
    {
      "from": "A_828",
      "to": "BF_220",
      "type": "OPERATES",
      "evidence": [
        "EV_003366"
      ],
      "confidence": 0.76,
      "status": "verified"
    },
    {
      "from": "A_828",
      "to": "BF_221",
      "type": "OPERATES",
      "evidence": [
        "EV_003367"
      ],
      "confidence": 0.78,
      "status": "verified"
    },
    {
      "from": "A_828",
      "to": "BF_222",
      "type": "OPERATES",
      "evidence": [
        "EV_003368"
      ],
      "confidence": 0.78,
      "status": "verified"
    },
    {
      "from": "A_829",
      "to": "BF_222",
      "type": "OPERATES",
      "evidence": [
        "EV_003369"
      ],
      "confidence": 0.78,
      "status": "verified"
    },
    {
      "from": "A_830",
      "to": "BF_222",
      "type": "OPERATES",
      "evidence": [
        "EV_003370"
      ],
      "confidence": 0.78,
      "status": "verified"
    },
    {
      "from": "A_328",
      "to": "BF_222",
      "type": "OPERATES",
      "evidence": [
        "EV_003371"
      ],
      "confidence": 0.8,
      "status": "verified"
    },
    {
      "from": "A_328",
      "to": "BF_011",
      "type": "OPERATES",
      "evidence": [
        "EV_003372"
      ],
      "confidence": 0.8,
      "status": "verified"
    },
    {
      "from": "A_326",
      "to": "BF_011",
      "type": "OPERATES",
      "evidence": [
        "EV_003373"
      ],
      "confidence": 0.83,
      "status": "verified"
    },
    {
      "from": "A_831",
      "to": "BF_011",
      "type": "OPERATES",
      "evidence": [
        "EV_003374"
      ],
      "confidence": 0.76,
      "status": "verified"
    },
    {
      "from": "A_831",
      "to": "BF_223",
      "type": "OPERATES",
      "evidence": [
        "EV_003375"
      ],
      "confidence": 0.78,
      "status": "verified"
    },
    {
      "from": "A_832",
      "to": "BF_224",
      "type": "OPERATES",
      "evidence": [
        "EV_003376"
      ],
      "confidence": 0.76,
      "status": "verified"
    },
    {
      "from": "A_833",
      "to": "BF_225",
      "type": "OPERATES",
      "evidence": [
        "EV_003377"
      ],
      "confidence": 0.72,
      "status": "verified"
    },
    {
      "from": "M_387",
      "to": "T_115",
      "type": "IMPACTS",
      "evidence": [
        "EV_003378"
      ],
      "confidence": 0.72,
      "status": "verified"
    },
    {
      "from": "M_038",
      "to": "T_115",
      "type": "IMPACTS",
      "evidence": [
        "EV_003379"
      ],
      "confidence": 0.7,
      "status": "verified"
    },
    {
      "from": "M_346",
      "to": "T_115",
      "type": "IMPACTS",
      "evidence": [
        "EV_003380"
      ],
      "confidence": 0.7,
      "status": "verified"
    },
    {
      "from": "A_828",
      "to": "C_2230",
      "type": "HAS_TRAIT",
      "evidence": [
        "EV_003518"
      ],
      "confidence": 0.8,
      "status": "verified"
    },
    {
      "from": "A_829",
      "to": "C_2231",
      "type": "HAS_TRAIT",
      "evidence": [
        "EV_003519"
      ],
      "confidence": 0.8,
      "status": "verified"
    },
    {
      "from": "A_830",
      "to": "C_2232",
      "type": "HAS_TRAIT",
      "evidence": [
        "EV_003520"
      ],
      "confidence": 0.78,
      "status": "verified"
    },
    {
      "from": "A_328",
      "to": "C_2233",
      "type": "HAS_TRAIT",
      "evidence": [
        "EV_003521"
      ],
      "confidence": 0.82,
      "status": "verified"
    },
    {
      "from": "A_326",
      "to": "C_2234",
      "type": "HAS_TRAIT",
      "evidence": [
        "EV_003522"
      ],
      "confidence": 0.83,
      "status": "verified"
    },
    {
      "from": "A_831",
      "to": "C_2235",
      "type": "HAS_TRAIT",
      "evidence": [
        "EV_003523"
      ],
      "confidence": 0.78,
      "status": "verified"
    },
    {
      "from": "A_832",
      "to": "C_2236",
      "type": "HAS_TRAIT",
      "evidence": [
        "EV_003524"
      ],
      "confidence": 0.76,
      "status": "verified"
    },
    {
      "from": "A_833",
      "to": "C_2237",
      "type": "HAS_TRAIT",
      "evidence": [
        "EV_003525"
      ],
      "confidence": 0.72,
      "status": "verified"
    }
  ],
  "links": [
    {
      "from": "A_828",
      "to": "T_115",
      "type": "THEMED_AS",
      "evidence": [
        "EV_003356"
      ],
      "confidence": 0.8,
      "status": "verified"
    },
    {
      "from": "A_829",
      "to": "T_115",
      "type": "THEMED_AS",
      "evidence": [
        "EV_003357"
      ],
      "confidence": 0.8,
      "status": "verified"
    },
    {
      "from": "A_830",
      "to": "T_115",
      "type": "THEMED_AS",
      "evidence": [
        "EV_003358"
      ],
      "confidence": 0.78,
      "status": "verified"
    },
    {
      "from": "A_328",
      "to": "T_115",
      "type": "THEMED_AS",
      "evidence": [
        "EV_003359"
      ],
      "confidence": 0.82,
      "status": "verified"
    },
    {
      "from": "A_326",
      "to": "T_115",
      "type": "THEMED_AS",
      "evidence": [
        "EV_003360"
      ],
      "confidence": 0.83,
      "status": "verified"
    },
    {
      "from": "A_831",
      "to": "T_115",
      "type": "THEMED_AS",
      "evidence": [
        "EV_003361"
      ],
      "confidence": 0.78,
      "status": "verified"
    },
    {
      "from": "A_832",
      "to": "T_115",
      "type": "THEMED_AS",
      "evidence": [
        "EV_003362"
      ],
      "confidence": 0.76,
      "status": "verified"
    },
    {
      "from": "A_833",
      "to": "T_115",
      "type": "THEMED_AS",
      "evidence": [
        "EV_003363"
      ],
      "confidence": 0.72,
      "status": "verified"
    },
    {
      "from": "A_828",
      "to": "BF_218",
      "type": "OPERATES",
      "evidence": [
        "EV_003364"
      ],
      "confidence": 0.76,
      "status": "verified"
    },
    {
      "from": "A_828",
      "to": "BF_219",
      "type": "OPERATES",
      "evidence": [
        "EV_003365"
      ],
      "confidence": 0.76,
      "status": "verified"
    },
    {
      "from": "A_828",
      "to": "BF_220",
      "type": "OPERATES",
      "evidence": [
        "EV_003366"
      ],
      "confidence": 0.76,
      "status": "verified"
    },
    {
      "from": "A_828",
      "to": "BF_221",
      "type": "OPERATES",
      "evidence": [
        "EV_003367"
      ],
      "confidence": 0.78,
      "status": "verified"
    },
    {
      "from": "A_828",
      "to": "BF_222",
      "type": "OPERATES",
      "evidence": [
        "EV_003368"
      ],
      "confidence": 0.78,
      "status": "verified"
    },
    {
      "from": "A_829",
      "to": "BF_222",
      "type": "OPERATES",
      "evidence": [
        "EV_003369"
      ],
      "confidence": 0.78,
      "status": "verified"
    },
    {
      "from": "A_830",
      "to": "BF_222",
      "type": "OPERATES",
      "evidence": [
        "EV_003370"
      ],
      "confidence": 0.78,
      "status": "verified"
    },
    {
      "from": "A_328",
      "to": "BF_222",
      "type": "OPERATES",
      "evidence": [
        "EV_003371"
      ],
      "confidence": 0.8,
      "status": "verified"
    },
    {
      "from": "A_328",
      "to": "BF_011",
      "type": "OPERATES",
      "evidence": [
        "EV_003372"
      ],
      "confidence": 0.8,
      "status": "verified"
    },
    {
      "from": "A_326",
      "to": "BF_011",
      "type": "OPERATES",
      "evidence": [
        "EV_003373"
      ],
      "confidence": 0.83,
      "status": "verified"
    },
    {
      "from": "A_831",
      "to": "BF_011",
      "type": "OPERATES",
      "evidence": [
        "EV_003374"
      ],
      "confidence": 0.76,
      "status": "verified"
    },
    {
      "from": "A_831",
      "to": "BF_223",
      "type": "OPERATES",
      "evidence": [
        "EV_003375"
      ],
      "confidence": 0.78,
      "status": "verified"
    },
    {
      "from": "A_832",
      "to": "BF_224",
      "type": "OPERATES",
      "evidence": [
        "EV_003376"
      ],
      "confidence": 0.76,
      "status": "verified"
    },
    {
      "from": "A_833",
      "to": "BF_225",
      "type": "OPERATES",
      "evidence": [
        "EV_003377"
      ],
      "confidence": 0.72,
      "status": "verified"
    },
    {
      "from": "M_387",
      "to": "T_115",
      "type": "IMPACTS",
      "evidence": [
        "EV_003378"
      ],
      "confidence": 0.72,
      "status": "verified"
    },
    {
      "from": "M_038",
      "to": "T_115",
      "type": "IMPACTS",
      "evidence": [
        "EV_003379"
      ],
      "confidence": 0.7,
      "status": "verified"
    },
    {
      "from": "M_346",
      "to": "T_115",
      "type": "IMPACTS",
      "evidence": [
        "EV_003380"
      ],
      "confidence": 0.7,
      "status": "verified"
    },
    {
      "from": "A_828",
      "to": "C_2230",
      "type": "HAS_TRAIT",
      "evidence": [
        "EV_003518"
      ],
      "confidence": 0.8,
      "status": "verified"
    },
    {
      "from": "A_829",
      "to": "C_2231",
      "type": "HAS_TRAIT",
      "evidence": [
        "EV_003519"
      ],
      "confidence": 0.8,
      "status": "verified"
    },
    {
      "from": "A_830",
      "to": "C_2232",
      "type": "HAS_TRAIT",
      "evidence": [
        "EV_003520"
      ],
      "confidence": 0.78,
      "status": "verified"
    },
    {
      "from": "A_328",
      "to": "C_2233",
      "type": "HAS_TRAIT",
      "evidence": [
        "EV_003521"
      ],
      "confidence": 0.82,
      "status": "verified"
    },
    {
      "from": "A_326",
      "to": "C_2234",
      "type": "HAS_TRAIT",
      "evidence": [
        "EV_003522"
      ],
      "confidence": 0.83,
      "status": "verified"
    },
    {
      "from": "A_831",
      "to": "C_2235",
      "type": "HAS_TRAIT",
      "evidence": [
        "EV_003523"
      ],
      "confidence": 0.78,
      "status": "verified"
    },
    {
      "from": "A_832",
      "to": "C_2236",
      "type": "HAS_TRAIT",
      "evidence": [
        "EV_003524"
      ],
      "confidence": 0.76,
      "status": "verified"
    },
    {
      "from": "A_833",
      "to": "C_2237",
      "type": "HAS_TRAIT",
      "evidence": [
        "EV_003525"
      ],
      "confidence": 0.72,
      "status": "verified"
    }
  ]
}