{
  "schemaVersion": "v5",
  "themeId": "T_493",
  "themeName": "(Y15) 드론 / 3D프린팅",
  "meta": {
    "periodDefault": "3d",
    "periodOptions": [
      "1d",
      "3d",
      "7d",
      "15d",
      "1m",
      "ytd",
      "1y",
      "2y",
      "3y"
    ],
    "dataAsOf": "2026-06-24T00:00:00+09:00",
    "description": "2013~2015 소비자 가젯 붐(드론·3D프린팅)의 버블과 붕괴, 그리고 산업용 생존의 회고. 3D프린팅(3D Systems·Stratasys·Proto Labs·Materialise·Autodesk)·드론(AeroVironment·Kratos). 소비자 붐→산업용 전환·버블 경계의 교훈.",
    "notes": "T_493 신규 — 2015 회고 테마(Y15). 자산별 CHARACTER, MACRO 3(기존 재사용)",
    "sources": []
  },
  "nodes": [
    {
      "id": "T_493",
      "type": "THEME",
      "name": "(Y15) 드론 / 3D프린팅"
    },
    {
      "id": "A_2514",
      "type": "ASSET",
      "name": "3D시스템즈",
      "exposure": {
        "ticker": "DDD",
        "exchange": "NYSE",
        "country": "US"
      },
      "metrics": {
        "return_1d": 1.4134275618374659,
        "return_3d": -3.0405405405405372,
        "return_7d": -2.7118644067796627,
        "return_15d": -4.6511627906976605,
        "return_1m": -6.514657980456018,
        "return_ytd": 55.13513513513513,
        "return_1y": 66.86046511627907,
        "return_2y": -3.367003367003374,
        "return_3y": -71.55599603567889,
        "close": 2.87,
        "marketCap": 468785800,
        "pe_ttm": null,
        "valuationAsOf": "2026-07-07",
        "valuationSource": "FMP",
        "returnsAsOf": "2026-07-07",
        "returnsSource": "FMP"
      }
    },
    {
      "id": "C_1097",
      "type": "CHARACTER",
      "name": "3D프린팅 버블 상징"
    },
    {
      "id": "A_2515",
      "type": "ASSET",
      "name": "스트라타시스",
      "exposure": {
        "ticker": "SSYS",
        "exchange": "NASDAQ",
        "country": "US"
      },
      "metrics": {
        "return_1d": -3.0696576151121535,
        "return_3d": -3.1839622641509413,
        "return_7d": -1.4405762304921854,
        "return_15d": -7.959641255605376,
        "return_1m": -14.121338912133885,
        "return_ytd": -8.879023307436174,
        "return_1y": -29.829059829059823,
        "return_2y": -1.0843373493975905,
        "return_3y": -54.26183844011141,
        "close": 8.21,
        "marketCap": 712742940,
        "pe_ttm": null,
        "valuationAsOf": "2026-07-07",
        "valuationSource": "FMP",
        "returnsAsOf": "2026-07-07",
        "returnsSource": "FMP"
      }
    },
    {
      "id": "C_1098",
      "type": "CHARACTER",
      "name": "3D프린팅 양대 산맥"
    },
    {
      "id": "A_2516",
      "type": "ASSET",
      "name": "프로토랩스",
      "exposure": {
        "ticker": "PRLB",
        "exchange": "NYSE",
        "country": "US"
      },
      "metrics": {
        "return_1d": -3.6038371791547896,
        "return_3d": -5.56261112522225,
        "return_7d": -8.446195518345235,
        "return_15d": -5.801874841651888,
        "return_1m": -0.588235294117645,
        "return_ytd": 44.81012658227848,
        "return_1y": 80.616954092786,
        "return_2y": 149.1122278056951,
        "return_3y": 111.61070005691518,
        "close": 74.36,
        "marketCap": 1769321840,
        "pe_ttm": null,
        "valuationAsOf": "2026-07-07",
        "valuationSource": "FMP",
        "returnsAsOf": "2026-07-07",
        "returnsSource": "FMP"
      }
    },
    {
      "id": "C_1099",
      "type": "CHARACTER",
      "name": "디지털 제조 — 흑자 모델"
    },
    {
      "id": "A_2517",
      "type": "ASSET",
      "name": "머터리얼라이즈",
      "exposure": {
        "ticker": "MTLS",
        "exchange": "NASDAQ",
        "country": "US"
      },
      "metrics": {
        "return_1d": -3.825136612021862,
        "return_3d": -0.9845288326301049,
        "return_7d": 2.1770682148040787,
        "return_15d": 5.705705705705699,
        "return_1m": 4.918032786885251,
        "return_ytd": 29.17431192660551,
        "return_1y": 22.64808362369337,
        "return_2y": 43.67346938775509,
        "return_3y": -17.757009345794394,
        "close": 7.04,
        "marketCap": 412231924,
        "pe_ttm": null,
        "valuationAsOf": "2026-07-07",
        "valuationSource": "FMP",
        "returnsAsOf": "2026-07-07",
        "returnsSource": "FMP"
      }
    },
    {
      "id": "C_1100",
      "type": "CHARACTER",
      "name": "3D 소프트웨어·의료"
    },
    {
      "id": "A_043",
      "type": "ASSET",
      "name": "오토데스크",
      "exposure": {
        "ticker": "ADSK",
        "exchange": "NASDAQ",
        "country": "US"
      },
      "metrics": {
        "return_1d": 2.33208056278309,
        "return_3d": 6.317581097316793,
        "return_7d": 11.938017182311711,
        "return_15d": 7.030186967696417,
        "return_1m": -9.099469268960792,
        "return_ytd": -25.930317720503616,
        "return_1y": -32.931219604623266,
        "return_2y": -13.606964162225932,
        "return_3y": 3.0070811911921513,
        "close": 212.38,
        "marketCap": 44843028407,
        "pe_ttm": null,
        "valuationAsOf": "2026-07-07",
        "valuationSource": "FMP",
        "returnsAsOf": "2026-07-07",
        "returnsSource": "FMP"
      }
    },
    {
      "id": "C_1101",
      "type": "CHARACTER",
      "name": "설계 SW — 3D 생태계"
    },
    {
      "id": "A_271",
      "type": "ASSET",
      "name": "에어로바이론먼트",
      "exposure": {
        "ticker": "AVAV",
        "exchange": "NASDAQ",
        "country": "US"
      },
      "metrics": {
        "return_1d": -8.092060619769281,
        "return_3d": -5.746926467176983,
        "return_7d": 18.912788996195484,
        "return_15d": -4.719193340368166,
        "return_1m": -20.484344422700584,
        "return_ytd": -36.55880401264686,
        "return_1y": -33.99260853673395,
        "return_2y": -7.479933967097397,
        "return_3y": 62.41630858399121,
        "close": 162.53,
        "marketCap": 8225318240,
        "pe_ttm": null,
        "valuationAsOf": "2026-07-07",
        "valuationSource": "FMP",
        "returnsAsOf": "2026-07-07",
        "returnsSource": "FMP"
      }
    },
    {
      "id": "C_1102",
      "type": "CHARACTER",
      "name": "드론 — 소비자→방산 전환"
    },
    {
      "id": "A_270",
      "type": "ASSET",
      "name": "크라토스",
      "exposure": {
        "ticker": "KTOS",
        "exchange": "NASDAQ",
        "country": "US"
      },
      "metrics": {
        "return_1d": -5.976839745984308,
        "return_3d": -5.090497737556554,
        "return_7d": 8.678756476683947,
        "return_15d": -12.831168831168826,
        "return_1m": -20.599369085173493,
        "return_ytd": -36.51153991676126,
        "return_1y": 12.718316166592047,
        "return_2y": 155.0151975683891,
        "return_3y": 244.08749145591253,
        "close": 50.34,
        "marketCap": 9439755995,
        "pe_ttm": null,
        "valuationAsOf": "2026-07-07",
        "valuationSource": "FMP",
        "returnsAsOf": "2026-07-07",
        "returnsSource": "FMP"
      }
    },
    {
      "id": "C_1103",
      "type": "CHARACTER",
      "name": "무인·표적 드론"
    },
    {
      "id": "M_028",
      "type": "MACRO",
      "name": "자동화확산"
    },
    {
      "id": "M_114",
      "type": "MACRO",
      "name": "로보틱스확대"
    },
    {
      "id": "M_302",
      "type": "MACRO",
      "name": "위험자산선호심리"
    }
  ],
  "edges": [
    {
      "from": "A_2514",
      "to": "T_493",
      "type": "THEMED_AS"
    },
    {
      "from": "A_2514",
      "to": "C_1097",
      "type": "HAS_TRAIT"
    },
    {
      "from": "A_2515",
      "to": "T_493",
      "type": "THEMED_AS"
    },
    {
      "from": "A_2515",
      "to": "C_1098",
      "type": "HAS_TRAIT"
    },
    {
      "from": "A_2516",
      "to": "T_493",
      "type": "THEMED_AS"
    },
    {
      "from": "A_2516",
      "to": "C_1099",
      "type": "HAS_TRAIT"
    },
    {
      "from": "A_2517",
      "to": "T_493",
      "type": "THEMED_AS"
    },
    {
      "from": "A_2517",
      "to": "C_1100",
      "type": "HAS_TRAIT"
    },
    {
      "from": "A_043",
      "to": "T_493",
      "type": "THEMED_AS"
    },
    {
      "from": "A_043",
      "to": "C_1101",
      "type": "HAS_TRAIT"
    },
    {
      "from": "A_271",
      "to": "T_493",
      "type": "THEMED_AS"
    },
    {
      "from": "A_271",
      "to": "C_1102",
      "type": "HAS_TRAIT"
    },
    {
      "from": "A_270",
      "to": "T_493",
      "type": "THEMED_AS"
    },
    {
      "from": "A_270",
      "to": "C_1103",
      "type": "HAS_TRAIT"
    },
    {
      "from": "M_028",
      "to": "T_493",
      "type": "IMPACTS"
    },
    {
      "from": "M_114",
      "to": "T_493",
      "type": "IMPACTS"
    },
    {
      "from": "M_302",
      "to": "T_493",
      "type": "IMPACTS"
    }
  ],
  "links": [
    {
      "from": "A_2514",
      "to": "T_493",
      "type": "THEMED_AS"
    },
    {
      "from": "A_2514",
      "to": "C_1097",
      "type": "HAS_TRAIT"
    },
    {
      "from": "A_2515",
      "to": "T_493",
      "type": "THEMED_AS"
    },
    {
      "from": "A_2515",
      "to": "C_1098",
      "type": "HAS_TRAIT"
    },
    {
      "from": "A_2516",
      "to": "T_493",
      "type": "THEMED_AS"
    },
    {
      "from": "A_2516",
      "to": "C_1099",
      "type": "HAS_TRAIT"
    },
    {
      "from": "A_2517",
      "to": "T_493",
      "type": "THEMED_AS"
    },
    {
      "from": "A_2517",
      "to": "C_1100",
      "type": "HAS_TRAIT"
    },
    {
      "from": "A_043",
      "to": "T_493",
      "type": "THEMED_AS"
    },
    {
      "from": "A_043",
      "to": "C_1101",
      "type": "HAS_TRAIT"
    },
    {
      "from": "A_271",
      "to": "T_493",
      "type": "THEMED_AS"
    },
    {
      "from": "A_271",
      "to": "C_1102",
      "type": "HAS_TRAIT"
    },
    {
      "from": "A_270",
      "to": "T_493",
      "type": "THEMED_AS"
    },
    {
      "from": "A_270",
      "to": "C_1103",
      "type": "HAS_TRAIT"
    },
    {
      "from": "M_028",
      "to": "T_493",
      "type": "IMPACTS"
    },
    {
      "from": "M_114",
      "to": "T_493",
      "type": "IMPACTS"
    },
    {
      "from": "M_302",
      "to": "T_493",
      "type": "IMPACTS"
    }
  ]
}